gd_mmtsp-0.1.2.dist-info/licenses/LICENSE
mmtsp/__init__.py
mmtsp/cli.py
gd_mmtsp-0.1.2.dist-info/METADATA
gd_mmtsp-0.1.2.dist-info/WHEEL
gd_mmtsp-0.1.2.dist-info/entry_points.txt
gd_mmtsp-0.1.2.dist-info/top_level.txt
gd_mmtsp-0.1.2.dist-info/RECORD
