Metadata-Version: 2.4
Name: gd-mmtsp
Version: 0.1.2
Summary: MMTSP: Automate mmt sri and push commands with commit message and prefix.
Author-email: Glendale Designs <info@glendaledesigns.com>
License: Copyright (C) Glendale Designs, Inc - All Rights Reserved
License-File: LICENSE
Dynamic: license-file
